Metadata-Version: 2.4
Name: mcp-table-editor
Version: 0.1.2
Summary: Add your description here
License: Apache-2.0
Requires-Python: >=3.10
Requires-Dist: fastapi>=0.115.12
Requires-Dist: fastmcp>=2.3.0
Requires-Dist: mcp>=1.6.0
Requires-Dist: pandas>=2.2.3
Requires-Dist: python-ulid>=3.0.0
Requires-Dist: sqlalchemy>=2.0.40
